<?xml version="1.0"?>
<sudokuImage>
  <image uri="image60.JPG">
    <camera brand="sonyEricsson" model="s500i"/>
    <quality deformation="2" light="3" rotation="4" blur="1" shadow="1"/>
    <imageSpecifications sizex="640" sizey="480" bitsPP="24" encoding="JPG"/>
  </image>
  <sudoku labelling="Human">
    <gridPosition>
      <upLeft x="145" y="55"/>
      <upRight x="551" y="59"/>
      <downLeft x="151" y="438"/>
      <downRight x="535" y="458"/>
    </gridPosition>
    <row rowId="1">
      <col colId="1" cellValue="0"/>
      <col colId="2" cellValue="0"/>
      <col colId="3" cellValue="0"/>
      <col colId="4" cellValue="8"/>
      <col colId="5" cellValue="2"/>
      <col colId="6" cellValue="7"/>
      <col colId="7" cellValue="9"/>
      <col colId="8" cellValue="4"/>
      <col colId="9" cellValue="0"/>
    </row>
    <row rowId="2">
      <col colId="1" cellValue="0"/>
      <col colId="2" cellValue="5"/>
      <col colId="3" cellValue="4"/>
      <col colId="4" cellValue="3"/>
      <col colId="5" cellValue="1"/>
      <col colId="6" cellValue="0"/>
      <col colId="7" cellValue="0"/>
      <col colId="8" cellValue="0"/>
      <col colId="9" cellValue="0"/>
    </row>
    <row rowId="3">
      <col colId="1" cellValue="8"/>
      <col colId="2" cellValue="0"/>
      <col colId="3" cellValue="0"/>
      <col colId="4" cellValue="0"/>
      <col colId="5" cellValue="6"/>
      <col colId="6" cellValue="0"/>
      <col colId="7" cellValue="0"/>
      <col colId="8" cellValue="0"/>
      <col colId="9" cellValue="1"/>
    </row>
    <row rowId="4">
      <col colId="1" cellValue="0"/>
      <col colId="2" cellValue="0"/>
      <col colId="3" cellValue="0"/>
      <col colId="4" cellValue="6"/>
      <col colId="5" cellValue="0"/>
      <col colId="6" cellValue="1"/>
      <col colId="7" cellValue="0"/>
      <col colId="8" cellValue="0"/>
      <col colId="9" cellValue="8"/>
    </row>
    <row rowId="5">
      <col colId="1" cellValue="0"/>
      <col colId="2" cellValue="7"/>
      <col colId="3" cellValue="8"/>
      <col colId="4" cellValue="9"/>
      <col colId="5" cellValue="0"/>
      <col colId="6" cellValue="3"/>
      <col colId="7" cellValue="5"/>
      <col colId="8" cellValue="6"/>
      <col colId="9" cellValue="0"/>
    </row>
    <row rowId="6">
      <col colId="1" cellValue="6"/>
      <col colId="2" cellValue="0"/>
      <col colId="3" cellValue="0"/>
      <col colId="4" cellValue="5"/>
      <col colId="5" cellValue="0"/>
      <col colId="6" cellValue="2"/>
      <col colId="7" cellValue="0"/>
      <col colId="8" cellValue="0"/>
      <col colId="9" cellValue="0"/>
    </row>
    <row rowId="7">
      <col colId="1" cellValue="4"/>
      <col colId="2" cellValue="0"/>
      <col colId="3" cellValue="0"/>
      <col colId="4" cellValue="0"/>
      <col colId="5" cellValue="3"/>
      <col colId="6" cellValue="0"/>
      <col colId="7" cellValue="0"/>
      <col colId="8" cellValue="0"/>
      <col colId="9" cellValue="7"/>
    </row>
    <row rowId="8">
      <col colId="1" cellValue="0"/>
      <col colId="2" cellValue="0"/>
      <col colId="3" cellValue="0"/>
      <col colId="4" cellValue="0"/>
      <col colId="5" cellValue="9"/>
      <col colId="6" cellValue="6"/>
      <col colId="7" cellValue="1"/>
      <col colId="8" cellValue="8"/>
      <col colId="9" cellValue="0"/>
    </row>
    <row rowId="9">
      <col colId="1" cellValue="0"/>
      <col colId="2" cellValue="8"/>
      <col colId="3" cellValue="6"/>
      <col colId="4" cellValue="1"/>
      <col colId="5" cellValue="5"/>
      <col colId="6" cellValue="4"/>
      <col colId="7" cellValue="0"/>
      <col colId="8" cellValue="0"/>
      <col colId="9" cellValue="0"/>
    </row>
  </sudoku>
</sudokuImage>
